tempconvert/__init__.py
tempconvert-1.0.dist-info/LICENCE.txt
tempconvert-1.0.dist-info/METADATA
tempconvert-1.0.dist-info/WHEEL
tempconvert-1.0.dist-info/top_level.txt
tempconvert-1.0.dist-info/RECORD
