Metadata-Version: 2.1
Name: tempconvert
Version: 1.0
Summary: A package for temperature conversion
Home-page: UNKNOWN
Author: Md. Rasel Meya
Author-email: raselmeya2194@gmail.com
License: UNKNOWN
Platform: UNKNOWN
Classifier: Programming Language :: Python :: 3
Classifier: License :: OSI Approved :: MIT License
Classifier: Operating System :: OS Independent
